data_memory_unit.v
module data_memory_unit(clk,address,write_data,write_enable,read_enable,read_data);

input clk;
input[31:0] address;
input[31:0] write_data;
input write_enable, read_enable;

output[31:0] read_data;

  
reg[31:0] main_memory[511:0];  

wire[31:0] main_address = address[31:0];

initial 
begin  
//Matrix A
main_memory[0] = 32'd1;
main_memory[1] = 32'd2;
main_memory[2] = 32'd4;
main_memory[3] = 32'd5;

//Matrix B
main_memory[4] = 32'd3;
main_memory[5] = 32'd6;
main_memory[6] = 32'd8;
main_memory[7] = 32'd9;

main_memory[8] = 32'd3;
main_memory[9] = 32'd1;
main_memory[10] = 32'd2;
main_memory[11] = 32'd3;
main_memory[12] = 32'd1;
main_memory[13] = 32'd2;
main_memory[14] = 32'd3;
main_memory[15] = 32'd1;
main_memory[16] = 32'd2;
main_memory[17] = 32'd3;


main_memory[18] = 32'd0;
main_memory[19] = 32'd0;
main_memory[20] = 32'd0;
main_memory[21] = 32'd0;
main_memory[22] = 32'd0;
main_memory[23] = 32'd0;
main_memory[24] = 32'd0;
main_memory[25] = 32'd0;
main_memory[26] = 32'd0;

end  

always @(*) 
begin  
  if(write_enable)
  begin  
    main_memory[main_address] = write_data;
  end  
end  

assign read_data = (read_enable == 1'b1) ? main_memory[main_address]:32'd0;

endmodule

alu.v
module alu(clk,data_1,data_2,alu_cntrl,alu_out,zero);
    input[3:0]alu_cntrl;
    input clk;
    input[31:0]data_1, data_2;
    output reg[31:0] alu_out;
    output reg zero;

    always@(posedge clk)
    begin
        zero = 0;
        case(alu_cntrl)
            4'b0000: alu_out <= data_1 & data_2;
            4'b0001: alu_out <= data_1 | data_2;
            4'b0010: alu_out <= data_1 + data_2;
            4'b0011: alu_out <= data_1 - data_2;
            4'b0100: alu_out <= data_1 * data_2;
        endcase
        if(alu_out == 0)
            zero = 1;
    end
endmodule

alu_control_unit.v
module alu_control_unit(clk,func,alu_op,alu_control);

input clk;
input[5:0] func;
input[1:0] alu_op;
output[3:0] alu_control;

reg[3:0] alu_control;

always @(posedge clk)
begin
  case(alu_op)
    2'b00 : 
        //For LW and SW
        alu_control = 4'b0010; 
    2'b01 : 
        //For BEQ
        alu_control = 4'b0011; 
    2'b10 : // For R-type instructions
        begin
        if(func == 6'b100000) 
        begin
            //For ADD
            alu_control = 4'b0010;
        end
        else if(func == 6'b100001) 
        begin
            //For MULT
            alu_control = 4'b0100;
        end
        end
  endcase
end

endmodule

register_file.v
module register_file(clk,read_reg1,read_reg2,write_reg,write_data,reg_write,read_data1,read_data2);

input clk;
input[4:0] read_reg1;
input[4:0] read_reg2;
input[4:0] write_reg;
input[31:0] write_data;
input reg_write;

output[31:0] read_data1;
output[31:0] read_data2;

reg[31:0] read_data1;
reg[31:0] read_data2;

wire[4:0] read_reg1;
wire[4:0] read_reg2;
wire[4:0] write_reg;

//32 registers of 32-bits each
reg[31:0] all_registers[0:31];



//Initialising all the register values to 0
integer i;
initial 
begin  
  for(i = 0 ;i < 32 ;i = i + 1) 
      all_registers[i] <= 32'd0;  
end 



always @(*)
begin
  begin
  read_data1 = all_registers[read_reg1];
  read_data2 = all_registers[read_reg2];
  end
  if (reg_write == 1) 
  begin
  all_registers[write_reg] = write_data;
  end
  
end



always @(*)
begin
/*Matrix A*/
$display("A");
$display("%d %d",all_registers[1],all_registers[2]);
$display("%d %d",all_registers[3],all_registers[4]);
/*$display("A00%d",all_registers[1]);
$display("A01%d",all_registers[2]);
$display("A10%d",all_registers[3]);
$display("A11%d",all_registers[4]);
*/

/*Matrix B*/
$display("B");
$display("%d %d",all_registers[5],all_registers[6]);
$display("%d %d",all_registers[7],all_registers[8]);
/*$display("B00%d",all_registers[5]);
$display("B01%d",all_registers[6]);
$display("B10%d",all_registers[7]);
$display("B11%d",all_registers[8]);
*/

/*Matrix C = A * B*/
$display("C");
$display("%d %d",all_registers[20],all_registers[21]);
$display("%d %d",all_registers[22],all_registers[23]);
/*$display("C00%d",all_registers[20]);
$display("C01%d",all_registers[21]);
$display("C10%d",all_registers[22]);
$display("C11%d",all_registers[23]);
*/
$display("-----------------------------------");
end
 endmodule




// module register_decoder(clk,register, out);
//     input[4:0] register;
//     input clk;
//     output reg[31:0] out;
//     always@(posedge clk)
//     begin
//         case(register[2:0])
//             3'b000: out = 11;
//             3'b001: out = 23;
//             3'b010: out = 35;
//             3'b011: out = 9;
//             3'b100: out = 43;
//             3'b101: out = 2;
//             3'b110: out = 50;
//         endcase
//     end
// endmodule

control_unit.v
module control_unit(clk,opcode,reg_dst,memto_reg,alu_op,jump,branch,mem_read,mem_write,alu_src,reg_write);  
 
input clk;
input [5:0] opcode;

output reg[1:0] alu_op;
output reg memto_reg,reg_dst,jump, branch, mem_read, mem_write, alu_src, reg_write;

always @(*)  
begin 

//Default control signals
reg_dst = 1'b0;  
memto_reg = 1'b0;  
alu_op = 2'b00;  
jump = 1'b0;  
branch = 1'b0;  
mem_read = 1'b0;  
mem_write = 1'b0;  
alu_src = 1'b0;  
reg_write = 1'b0;    

    case(opcode)   
    6'b000000:  begin  //control lines for add/mult instruction  
                reg_dst = 1'b1;  
                memto_reg = 1'b0;  
                alu_op = 2'b10;  
                jump = 1'b0;  
                branch = 1'b0;  
                mem_read = 1'b0;  
                mem_write = 1'b0;  
                alu_src = 1'b0;  
                reg_write = 1'b1;  
                end  
        
    6'b100011:  begin //control lines for lw instruction 
                reg_dst = 1'b0;  
                memto_reg = 1'b1;  
                alu_op = 2'b00;  
                jump = 1'b0;  
                branch = 1'b0;  
                mem_read = 1'b1;  
                mem_write = 1'b0;  
                alu_src = 1'b1;  
                reg_write = 1'b1;  
                end 

    6'b101011:  begin //control lines for sw instruction 
                reg_dst = 1'b0;  
                memto_reg = 1'b0;  
                alu_op = 2'b00;  
                jump = 1'b0;  
                branch = 1'b0;  
                mem_read = 1'b0;  
                mem_write = 1'b1;  
                alu_src = 1'b1;  
                reg_write = 1'b0;
                end

    6'b000100:  begin //control lines for beq instruction  
                reg_dst = 1'b0;  
                memto_reg = 1'b0;  
                alu_op = 2'b01;  
                jump = 1'b0;  
                branch = 1'b1;  
                mem_read = 1'b0;  
                mem_write = 1'b0;  
                alu_src = 1'b0;  
                reg_write = 1'b0;   
                end

    6'b000010:  begin //control lines for j instruction  
                reg_dst = 1'b0;  
                memto_reg = 1'b0;  
                alu_op = 2'b00;  
                jump = 1'b1;  
                branch = 1'b0;  
                mem_read = 1'b0;  
                mem_write = 1'b0;  
                alu_src = 1'b0;  
                reg_write = 1'b0;   
                end
    endcase  
end    


endmodule

instruction_memory.v
module instruction_memory(clk,pc, instruction);

input clk;
input[31:0] pc;
output[31:0] instruction;
reg[31:0] instruction;

//256 registers of 32-bits each
reg[31:0] instr_memory[255:0]; 


//MIPS assembly program in binary format
initial 
begin

//LW instructions
instr_memory[0] = 32'b10001100000000010000000000000000;
instr_memory[1] = 32'b10001100000000100000000000000001;
instr_memory[2] = 32'b10001100000000110000000000000010;
instr_memory[3] = 32'b10001100000001000000000000000011;
instr_memory[4] = 32'b10001100000001010000000000000100;
instr_memory[5] = 32'b10001100000001100000000000000101;
instr_memory[6] = 32'b10001100000001110000000000000110;
instr_memory[7] = 32'b10001100000010000000000000000111;
instr_memory[8] = 32'b00000000001001010101000000100001;

//MULT and ADD instructions
instr_memory[9] = 32'b00000000001001010101000000100001; //1 and 5 to 10
instr_memory[10] = 32'b00000000010001110101100000100001; // 2 and 7 to 11
instr_memory[11] = 32'b00000000011001010110000000100001; // 3 and 5 to 12
instr_memory[12] = 32'b00000000100001110110100000100001; // 4 and 7 to 13
instr_memory[13] = 32'b00000000001001100111000000100001; //1 and 6 to 14
instr_memory[14] = 32'b00000000010010000111100000100001; // 2 and 8 to 15
instr_memory[15] = 32'b00000000011001101000000000100001; // 3 and 6 to 16
instr_memory[16] = 32'b00000000100010001000100000100001; // 4 and 8 to 17

//Output Matrix
instr_memory[17] = 32'b00000001010010111010000000100000; // 10 + 11 = 20
instr_memory[18] = 32'b00000001110011111010100000100000; // 14 + 15 = 21
instr_memory[19] = 32'b00000001100011011011000000100000; // 12 + 13 = 33
instr_memory[20] = 32'b00000010000100011011100000100000; // 16 + 17 = 23


//instr_memory[0] <= 32'b10001100000000000000000000000000
//instr_memory[1] <= 32'b10001100000000100000000000000010;
//instr_memory[2] <= 32'b10001100000000110000000000110000;
// instr_memory[8] <= 32'b10001100000010010000000000001000;
// instr_memory[9] <= 32'b10001100000010100000000000001001;
// instr_memory[10] <= 32'b10001100000010110000000000001010;
// instr_memory[11] <= 32'b10001100000011000000000000001011;
// instr_memory[12] <= 32'b10001100000011010000000000001100;
// instr_memory[13] <= 32'b10001100000011100000000000001101;
// instr_memory[14] <= 32'b10001100000011110000000000001110;
// instr_memory[15] <= 32'b10001100000100000000000000001111;
// instr_memory[16] <= 32'b10001100000100010000000000010000;
// instr_memory[17] <= 32'b10001100000100100000000000010001;
// instr_memory[12] <= 32'b00000001001010101010000000100000; 
// instr_memory[13] <= 32'b00000000010011011010100000100001;
// instr_memory[20] <= 32'b00000000011100001111000000100001;
// instr_memory[11] <= 32'b00000001001010100101100000100000;
// instr_memory[22] <= 32'b00000011101111101110000000100000;
// instr_memory[23] <= 32'b10101100000100110000000000011100;
// //C01;
// instr_memory[24] <= 32'b00000000001010110000000000100001;
// instr_memory[25] <= 32'b00000000010011101111100000100001;
// instr_memory[26] <= 32'b00000000011100011111000000100001;
// instr_memory[27] <= 32'b00000000000111111110100000100000;
// instr_memory[28] <= 32'b00000011101111101110000000100000;
// instr_memory[29] <= 32'b10101100000101000000000000011100;
// //C02;<
// instr_memory[30] <= 32'b00000000001011000000000000100001;
// instr_memory[31] <= 32'b00000000010011111111100000100001;
// instr_memory[32] <= 32'b00000000011100101111000000100001;
// instr_memory[33] <= 32'b00000000000111111110100000100000;
// instr_memory[34] <= 32'b00000011101111101110000000100000;
// instr_memory[35] <= 32'b10101100000101010000000000011100;
// //C10;<
// instr_memory[36] <= 32'b00000000100010100000000000100001;
// instr_memory[37] <= 32'b00000000101011011111100000100001;
// instr_memory[38] <= 32'b00000000110100001111000000100001;
// instr_memory[39] <= 32'b00000000000111111110100000100000;
// instr_memory[40] <= 32'b00000011101111101110000000100000;
// instr_memory[41] <= 32'b10101100000101100000000000011100;
// //C11;<
// instr_memory[42] <= 32'b00000000100010110000000000100001;
// instr_memory[43] <= 32'b00000000101011101111100000100001;
// instr_memory[44] <= 32'b00000000110100011111000000100001;
// instr_memory[45] <= 32'b00000000000111111110100000100000;
// instr_memory[46] <= 32'b00000011101111101110000000100000;
// instr_memory[47] <= 32'b10101100000101110000000000011100;
// //C12<
// instr_memory[48] <= 32'b00000000100011000000000000100001;
// instr_memory[49] <= 32'b00000000101011111111100000100001;
// instr_memory[50] <= 32'b00000000110100101111000000100001;
// instr_memory[51] <= 32'b00000000000111111110100000100000;
// instr_memory[52] <= 32'b00000011101111101110000000100000;
// instr_memory[53] <= 32'b10101100000110000000000000011100;
// //C20<
// instr_memory[54] <= 32'b00000000111010100000000000100001;
// instr_memory[55] <= 32'b00000001000011011111100000100001;
// instr_memory[56] <= 32'b00000001001100001111000000100001;
// instr_memory[57] <= 32'b00000000000111111110100000100000;
// instr_memory[58] <= 32'b00000011101111101110000000100000;
// instr_memory[59] <= 32'b10101100000110010000000000011100;
// //C21<
// instr_memory[60] <= 32'b00000000111010110000000000100001;
// instr_memory[61] <= 32'b00000001000011101111100000100001;
// instr_memory[62] <= 32'b00000001001100011111000000100001;
// instr_memory[63] <= 32'b00000000000111111110100000100000;
// instr_memory[64] <= 32'b00000011101111101110000000100000;
// instr_memory[65] <= 32'b10101100000110100000000000011100;
// //C22<
// instr_memory[66] <= 32'b00000000111010100000000000100001;
// instr_memory[67] <= 32'b00000001000011111111100000100001;
// instr_memory[68] <= 32'b00000001001100101111000000100001;
// instr_memory[69] <= 32'b00000000000111111110100000100000;
// instr_memory[70] <= 32'b00000011101111101110000000100000;
// instr_memory[71] <= 32'b10101100000110110000000000011100;
end


//Instruction fetch
always @(*)
begin
    instruction = instr_memory[pc];
end

endmodule

MIPS.v
/*MAIN MODULE*/
module mips(clk,reset,pc_nxt,result);

input clk;
input reset;
output[31:0] result;
output[31:0] pc_nxt;
reg[31:0] result;


/*PROGRAM COUNTER*/
reg[31:0] pc;
reg[31:0] extended;
reg[31:0] adder1;
reg[31:0] adder2;
reg sel;
reg[31:0] pc_nxt;
always @(posedge clk)
begin
    if(reset)
    begin
        pc_nxt = 31'd0;
        // $display("pc_nxt in reset state:");
        // $display("%d",pc_nxt);
    end
    else
    begin
        adder1 = pc+1;
        extended = extended << 2;
        adder2 = adder1+extended;
        sel = branch & zero;
        pc = sel ? adder2 : adder1;
        pc_nxt = pc;
    end
    pc = pc_nxt;
end


/*INSTRUCTION MEMORY*/
wire[31:0] instruction;
instruction_memory IM(clk,pc,instruction);


/*CONTROL UNIT*/
//Wires required
wire reg_dst, memto_reg, jump, branch, mem_read, mem_write, alu_src, reg_write;
wire[1:0] alu_op;
//Module
control_unit Control(clk,instruction[31:26],reg_dst,memto_reg,alu_op,jump,branch,mem_read,mem_write,alu_src,reg_write);  


/*REGISTER FILE*/
//Wires required
wire[4:0] write_reg;
wire[31:0] write_data,read_data1,read_data2;
//Mux for destination register
assign write_reg = (reg_dst == 1) ? instruction[15:11]:instruction[20:16];  
//Module 
register_file Registers(clk,instruction[25:21],instruction[20:16],write_reg,write_data,reg_write,read_data1,read_data2);


/*ALU CONTROL*/
//Wires required
wire[3:0] alu_control;
//Module
alu_control_unit ALU_control(clk,instruction[5:0],alu_op,alu_control);


/*ALU*/
//Wires required
wire[31:0] data_2;
wire[31:0] alu_result;
wire zero;
always @(*)
begin
//Sign extender
extended[31:0] = {{8{instruction[15]}},instruction[15:0]};
end
//Mux for ALU input
assign data_2 = (alu_src == 1) ? extended:read_data2; 
//Module
alu ALU(clk,read_data1,data_2,alu_control,alu_result,zero);


/*DATA MEMORY*/
//Wires required
wire[31:0] read_data;
//Module
data_memory_unit Data_memory(clk,alu_result,read_data2,mem_write,mem_read,read_data);
//Mux for writing back to the register file
assign write_data = (memto_reg == 1) ? read_data:alu_result;


endmodule

main_tb.v
module main_tb;

reg clk;
reg reset;
wire[31:0] result;
wire[31:0] pc_nxt;

mips uut
(
    .clk(clk),
    .reset(reset),
    .result(result),
    .pc_nxt(pc_nxt)
);

initial
begin
  $dumpfile("out.vcd");
  $dumpvars(0,main_tb);
    clk =0 ;
  clk = 1;
  reset = 1;

  #80
  reset = 0;
// clk =0;
// #80;
// clk =1;
  #2000
  $finish;
end

always
    #10 clk = ~clk;

endmodule

out.vcd
$date
	Tue Nov 27 12:07:35 2018
$end
$version
	Icarus Verilog
$end
$timescale
	1s
$end
$scope module main_tb $end
$var wire 32 ! result [31:0] $end
$var wire 32 " pc_nxt [31:0] $end
$var reg 1 # clk $end
$var reg 1 $ reset $end
$scope module uut $end
$var wire 1 # clk $end
$var wire 1 $ reset $end
$var wire 1 % zero $end
$var wire 5 & write_reg [4:0] $end
$var wire 32 ' write_data [31:0] $end
$var wire 1 ( reg_write $end
$var wire 1 ) reg_dst $end
$var wire 32 * read_data2 [31:0] $end
$var wire 32 + read_data1 [31:0] $end
$var wire 32 , read_data [31:0] $end
$var wire 1 - memto_reg $end
$var wire 1 . mem_write $end
$var wire 1 / mem_read $end
$var wire 1 0 jump $end
$var wire 32 1 instruction [31:0] $end
$var wire 32 2 data_2 [31:0] $end
$var wire 1 3 branch $end
$var wire 1 4 alu_src $end
$var wire 32 5 alu_result [31:0] $end
$var wire 2 6 alu_op [1:0] $end
$var wire 4 7 alu_control [3:0] $end
$var reg 32 8 adder1 [31:0] $end
$var reg 32 9 adder2 [31:0] $end
$var reg 32 : extended [31:0] $end
$var reg 32 ; pc [31:0] $end
$var reg 32 < pc_nxt [31:0] $end
$var reg 32 = result [31:0] $end
$var reg 1 > sel $end
$scope module ALU $end
$var wire 1 # clk $end
$var wire 32 ? data_2 [31:0] $end
$var wire 32 @ data_1 [31:0] $end
$var wire 4 A alu_cntrl [3:0] $end
$var reg 32 B alu_out [31:0] $end
$var reg 1 % zero $end
$upscope $end
$scope module ALU_control $end
$var wire 1 # clk $end
$var wire 6 C func [5:0] $end
$var wire 2 D alu_op [1:0] $end
$var reg 4 E alu_control [3:0] $end
$upscope $end
$scope module Control $end
$var wire 1 # clk $end
$var wire 6 F opcode [5:0] $end
$var reg 2 G alu_op [1:0] $end
$var reg 1 4 alu_src $end
$var reg 1 3 branch $end
$var reg 1 0 jump $end
$var reg 1 / mem_read $end
$var reg 1 . mem_write $end
$var reg 1 - memto_reg $end
$var reg 1 ) reg_dst $end
$var reg 1 ( reg_write $end
$upscope $end
$scope module Data_memory $end
$var wire 32 H address [31:0] $end
$var wire 1 # clk $end
$var wire 32 I main_address [31:0] $end
$var wire 1 / read_enable $end
$var wire 1 . write_enable $end
$var wire 32 J write_data [31:0] $end
$var wire 32 K read_data [31:0] $end
$upscope $end
$scope module IM $end
$var wire 1 # clk $end
$var wire 32 L pc [31:0] $end
$var reg 32 M instruction [31:0] $end
$upscope $end
$scope module Registers $end
$var wire 1 # clk $end
$var wire 5 N read_reg1 [4:0] $end
$var wire 5 O read_reg2 [4:0] $end
$var wire 1 ( reg_write $end
$var wire 32 P write_data [31:0] $end
$var wire 5 Q write_reg [4:0] $end
$var reg 32 R read_data1 [31:0] $end
$var reg 32 S read_data2 [31:0] $end
$var integer 32 T i [31:0] $end
$upscope $end
$upscope $end
$upscope $end
$enddefinitions $end
#0
$dumpvars
b100000 T
b0 S
b0 R
b1 Q
bx P
b1 O
b0 N
b10001100000000010000000000000000 M
b0 L
bx K
b0 J
bx I
bx H
b0 G
b100011 F
bx E
b0 D
b0 C
bx B
bx A
b0 @
b0 ?
x>
bx =
b0 <
b0 ;
b0 :
bx 9
bx 8
bx 7
b0 6
bx 5
14
03
b0 2
b10001100000000010000000000000000 1
00
1/
0.
1-
bx ,
b0 +
b0 *
0)
1(
bx '
b1 &
0%
1$
1#
b0 "
bx !
$end
#10
0#
#20
bx *
bx J
bx S
b1 '
b1 P
b1 ,
b1 K
1%
b0 I
b0 5
b0 B
b0 H
b10 7
b10 A
b10 E
1#
#30
0#
#40
1#
#50
0#
#60
1#
#70
0#
#80
b10 '
b10 P
b10 ,
b10 K
b1 I
b1 5
b1 B
b1 H
0%
b1 *
b1 J
b1 S
b10 &
b10 Q
b1 2
b1 ?
b1 C
b10 O
b1 :
b10001100000000100000000000000001 1
b10001100000000100000000000000001 M
b1 "
b1 <
b1 ;
b1 L
0>
b1 9
b1 8
1#
0$
#90
0#
#100
b100 '
b100 P
b11 *
b11 J
b11 S
b11 &
b11 Q
b100 ,
b100 K
b10 C
b11 O
b10 I
b10 5
b10 B
b10 H
b10001100000000110000000000000010 1
b10001100000000110000000000000010 M
b10 2
b10 ?
b10 "
b10 <
b10 ;
b10 L
b110 9
b10 :
b10 8
1#
#110
0#
#120
b101 '
b101 P
b11 *
b11 J
b11 S
b100 &
b100 Q
b101 ,
b101 K
b11 C
b100 O
b11 I
b11 5
b11 B
b11 H
b10001100000001000000000000000011 1
b10001100000001000000000000000011 M
b11 2
b11 ?
b11 "
b11 <
b11 ;
b11 L
b1011 9
b11 :
b11 8
1#
#130
0#
#140
b11 '
b11 P
b1 *
b1 J
b1 S
b101 &
b101 Q
b11 ,
b11 K
b100 C
b101 O
b100 I
b100 5
b100 B
b100 H
b10001100000001010000000000000100 1
b10001100000001010000000000000100 M
b100 2
b100 ?
b100 "
b100 <
b100 ;
b100 L
b10000 9
b100 :
b100 8
1#
#150
0#
#160
b110 '
b110 P
b10 *
b10 J
b10 S
b110 &
b110 Q
b110 ,
b110 K
b101 C
b110 O
b101 I
b101 5
b101 B
b101 H
b10001100000001100000000000000101 1
b10001100000001100000000000000101 M
b101 2
b101 ?
b101 "
b101 <
b101 ;
b101 L
b10101 9
b101 :
b101 8
1#
#170
0#
#180
b1000 '
b1000 P
b0 *
b0 J
b0 S
b111 &
b111 Q
b1000 ,
b1000 K
b110 C
b111 O
b110 I
b110 5
b110 B
b110 H
b10001100000001110000000000000110 1
b10001100000001110000000000000110 M
b110 2
b110 ?
b110 "
b110 <
b110 ;
b110 L
b11010 9
b110 :
b110 8
1#
#190
0#
#200
b0 *
b0 J
b0 S
b1001 '
b1001 P
b1000 &
b1000 Q
b1001 ,
b1001 K
b111 C
b1000 O
b111 I
b111 5
b111 B
b111 H
b10001100000010000000000000000111 1
b10001100000010000000000000000111 M
b111 2
b111 ?
b111 "
b111 <
b111 ;
b111 L
b11111 9
b111 :
b111 8
1#
#210
0#
#220
b100 '
b100 P
b11 *
b11 J
b11 S
b1 +
b1 @
b1 R
b1010 &
b1010 Q
b10 6
b10 D
b10 G
1)
1(
04
0/
0-
b0 ,
b0 K
b100001 C
b101 O
b1 N
b0 F
b100 I
b100 5
b100 B
b100 H
b1001010101000000100001 1
b1001010101000000100001 M
b11 2
b11 ?
b1000 "
b1000 <
b1000 ;
b1000 L
b100100 9
b101000000100001 :
b1000 8
1#
#230
0#
#240
b11 '
b11 P
b11 I
b11 5
b11 B
b11 H
b100 7
b100 A
b100 E
b1001 "
b1001 <
b1001 ;
b1001 L
b10100000010001101 9
b10100000010000100 :
b1001 8
1#
#250
0#
#260
b10000 '
b10000 P
b1000 2
b1000 ?
b10000 I
b10000 5
b10000 B
b10000 H
b1000 *
b1000 J
b1000 S
b10 +
b10 @
b10 R
b1011 &
b1011 Q
b111 O
b10 N
b10001110101100000100001 1
b10001110101100000100001 M
b1010 "
b1010 <
b1010 ;
b1010 L
b1010000001000011010 9
b101100000100001 :
b1010 8
1#
#270
0#
#280
b1100 '
b1100 P
b11 2
b11 ?
b1100 I
b1100 5
b1100 B
b1100 H
b11 *
b11 J
b11 S
b100 +
b100 @
b100 R
b1100 &
b1100 Q
b101 O
b11 N
b11001010110000000100001 1
b11001010110000000100001 M
b1011 "
b1011 <
b1011 ;
b1011 L
b10110000010001111 9
b110000000100001 :
b1011 8
1#
#290
0#
#300
b101000 '
b101000 P
b1000 2
b1000 ?
b101000 I
b101000 5
b101000 B
b101000 H
b1000 *
b1000 J
b1000 S
b101 +
b101 @
b101 R
b1101 &
b1101 Q
b111 O
b100 N
b100001110110100000100001 1
b100001110110100000100001 M
b1100 "
b1100 <
b1100 ;
b1100 L
b11000000010010000 9
b110100000100001 :
b1100 8
1#
#310
0#
#320
b110 '
b110 P
b110 2
b110 ?
b110 I
b110 5
b110 B
b110 H
b110 *
b110 J
b110 S
b1 +
b1 @
b1 R
b1110 &
b1110 Q
b110 O
b1 N
b1001100111000000100001 1
b1001100111000000100001 M
b1101 "
b1101 <
b1101 ;
b1101 L
b11010000010010001 9
b111000000100001 :
b1101 8
1#
#330
0#
#340
b10010 '
b10010 P
b1001 2
b1001 ?
b10010 I
b10010 5
b10010 B
b10010 H
b1001 *
b1001 J
b1001 S
b10 +
b10 @
b10 R
b1111 &
b1111 Q
b1000 O
b10 N
b10010000111100000100001 1
b10010000111100000100001 M
b1110 "
b1110 <
b1110 ;
b1110 L
b11100000010010010 9
b111100000100001 :
b1110 8
1#
#350
0#
#360
b11000 '
b11000 P
b110 2
b110 ?
b11000 I
b11000 5
b11000 B
b11000 H
b110 *
b110 J
b110 S
b100 +
b100 @
b100 R
b10000 &
b10000 Q
b110 O
b11 N
b11001101000000000100001 1
b11001101000000000100001 M
b1111 "
b1111 <
b1111 ;
b1111 L
b11110000010010011 9
b111111111000000000100001 :
b1111 8
1#
#370
0#
#380
b101101 '
b101101 P
b1001 2
b1001 ?
b101101 I
b101101 5
b101101 B
b101101 H
b1001 *
b1001 J
b1001 S
b101 +
b101 @
b101 R
b10001 &
b10001 Q
b1000 O
b100 N
b100010001000100000100001 1
b100010001000100000100001 M
b10000 "
b10000 <
b10000 ;
b10000 L
b11111111100000000010010100 9
b111111111000100000100001 :
b10000 8
1#
#390
0#
#400
b110000 '
b110000 P
b10000 2
b10000 ?
b110000 I
b110000 5
b110000 B
b110000 H
b10000 *
b10000 J
b10000 S
b11 +
b11 @
b11 R
b10100 &
b10100 Q
b100000 C
b1011 O
b1010 N
b1010010111010000000100000 1
b1010010111010000000100000 M
b10001 "
b10001 <
b10001 ;
b10001 L
b11111111100010000010010101 9
b111111111010000000100000 :
b10001 8
1#
#410
0#
#420
b10010 2
b10010 ?
b10101 &
b10101 Q
b10010 *
b10010 J
b10010 S
b110 +
b110 @
b110 R
b1111 O
b1110 N
b11000 '
b11000 P
b1110011111010100000100000 1
b1110011111010100000100000 M
b11000 I
b11000 5
b11000 B
b11000 H
b10010 "
b10010 <
b10010 ;
b10010 L
b11111111101000000010010010 9
b111111111010100000100000 :
b10010 8
b10 7
b10 A
b10 E
1#
#430
0#
#440
b110100 '
b110100 P
b101000 2
b101000 ?
b110100 I
b110100 5
b110100 B
b110100 H
b101000 *
b101000 J
b101000 S
b1100 +
b1100 @
b1100 R
b10110 &
b10110 Q
b1101 O
b1100 N
b1100011011011000000100000 1
b1100011011011000000100000 M
b10011 "
b10011 <
b10011 ;
b10011 L
b11111111101010000010010011 9
b111111111011000000100000 :
b10011 8
1#
#450
0#
#460
b1000101 '
b1000101 P
b101101 2
b101101 ?
b1000101 I
b1000101 5
b1000101 B
b1000101 H
b101101 *
b101101 J
b101101 S
b11000 +
b11000 @
b11000 R
b10111 &
b10111 Q
b10001 O
b10000 N
b10000100011011100000100000 1
b10000100011011100000100000 M
b10100 "
b10100 <
b10100 ;
b10100 L
b11111111101100000010010100 9
b111111111011100000100000 :
b10100 8
1#
#470
0#
#480
bx '
bx P
bx 2
bx ?
bx I
bx 5
bx B
bx H
bx *
bx J
bx S
bx +
bx @
bx R
bx &
bx Q
0(
b0 6
b0 D
b0 G
0)
bx C
bx O
bx N
bx F
bx 1
bx M
b10101 "
b10101 <
b10101 ;
b10101 L
b11111111101110000010010101 9
b0xxxxxxxxxxxxxxxxxxxxxxxx :
b10101 8
1#
#490
0#
#500
b10110 "
b10110 <
b10110 ;
b10110 L
bx 9
b0xxxxxxxxxxxxxxxxxxxxxxxx00 :
b10110 8
1#
#510
0#
#520
b10111 "
b10111 <
b10111 ;
b10111 L
b0xxxxxxxxxxxxxxxxxxxxxxxx0000 :
b10111 8
1#
#530
0#
#540
b11000 "
b11000 <
b11000 ;
b11000 L
b0xxxxxxxxxxxxxxxxxxxxxxxx000000 :
b11000 8
1#
#550
0#
#560
b11001 "
b11001 <
b11001 ;
b11001 L
bx00000000 :
b11001 8
1#
#570
0#
#580
b11010 "
b11010 <
b11010 ;
b11010 L
bx0000000000 :
b11010 8
1#
#590
0#
#600
b11011 "
b11011 <
b11011 ;
b11011 L
bx000000000000 :
b11011 8
1#
#610
0#
#620
b11100 "
b11100 <
b11100 ;
b11100 L
bx00000000000000 :
b11100 8
1#
#630
0#
#640
b11101 "
b11101 <
b11101 ;
b11101 L
bx0000000000000000 :
b11101 8
1#
#650
0#
#660
b11110 "
b11110 <
b11110 ;
b11110 L
bx000000000000000000 :
b11110 8
1#
#670
0#
#680
b11111 "
b11111 <
b11111 ;
b11111 L
bx00000000000000000000 :
b11111 8
1#
#690
0#
#700
b100000 "
b100000 <
b100000 ;
b100000 L
bx0000000000000000000000 :
b100000 8
1#
#710
0#
#720
b100001 "
b100001 <
b100001 ;
b100001 L
bx000000000000000000000000 :
b100001 8
1#
#730
0#
#740
b100010 "
b100010 <
b100010 ;
b100010 L
bx00000000000000000000000000 :
b100010 8
1#
#750
0#
#760
b100011 "
b100011 <
b100011 ;
b100011 L
bx0000000000000000000000000000 :
b100011 8
1#
#770
0#
#780
b100100 "
b100100 <
b100100 ;
b100100 L
bx000000000000000000000000000000 :
b100100 8
1#
#790
0#
#800
b100101 "
b100101 <
b100101 ;
b100101 L
b100101 9
b0 :
b100101 8
1#
#810
0#
#820
b100110 "
b100110 <
b100110 ;
b100110 L
b100110 9
b100110 8
1#
#830
0#
#840
b100111 "
b100111 <
b100111 ;
b100111 L
b100111 9
b100111 8
1#
#850
0#
#860
b101000 "
b101000 <
b101000 ;
b101000 L
b101000 9
b101000 8
1#
#870
0#
#880
b101001 "
b101001 <
b101001 ;
b101001 L
b101001 9
b101001 8
1#
#890
0#
#900
b101010 "
b101010 <
b101010 ;
b101010 L
b101010 9
b101010 8
1#
#910
0#
#920
b101011 "
b101011 <
b101011 ;
b101011 L
b101011 9
b101011 8
1#
#930
0#
#940
b101100 "
b101100 <
b101100 ;
b101100 L
b101100 9
b101100 8
1#
#950
0#
#960
b101101 "
b101101 <
b101101 ;
b101101 L
b101101 9
b101101 8
1#
#970
0#
#980
b101110 "
b101110 <
b101110 ;
b101110 L
b101110 9
b101110 8
1#
#990
0#
#1000
b101111 "
b101111 <
b101111 ;
b101111 L
b101111 9
b101111 8
1#
#1010
0#
#1020
b110000 "
b110000 <
b110000 ;
b110000 L
b110000 9
b110000 8
1#
#1030
0#
#1040
b110001 "
b110001 <
b110001 ;
b110001 L
b110001 9
b110001 8
1#
#1050
0#
#1060
b110010 "
b110010 <
b110010 ;
b110010 L
b110010 9
b110010 8
1#
#1070
0#
#1080
b110011 "
b110011 <
b110011 ;
b110011 L
b110011 9
b110011 8
1#
#1090
0#
#1100
b110100 "
b110100 <
b110100 ;
b110100 L
b110100 9
b110100 8
1#
#1110
0#
#1120
b110101 "
b110101 <
b110101 ;
b110101 L
b110101 9
b110101 8
1#
#1130
0#
#1140
b110110 "
b110110 <
b110110 ;
b110110 L
b110110 9
b110110 8
1#
#1150
0#
#1160
b110111 "
b110111 <
b110111 ;
b110111 L
b110111 9
b110111 8
1#
#1170
0#
#1180
b111000 "
b111000 <
b111000 ;
b111000 L
b111000 9
b111000 8
1#
#1190
0#
