data_memory_unit.v
module data_memory_unit(clk,address,write_data,write_enable,read_enable,read_data);

input clk;
input[31:0] address;
input[31:0] write_data;
input write_enable, read_enable;

output[31:0] read_data;

  
reg[31:0] main_memory[511:0];  

wire[31:0] main_address = address[31:0];

//loop for initialising the main memory
// integer i;
initial 
begin  
  // for(i = 0 ;i < 512 ;i = i + 1) 
  //       main_memory[i] <= 32'd0;  
  //matrix A
main_memory[0] = 32'd1;
main_memory[1] = 32'd2;
main_memory[2] = 32'd3;
main_memory[3] = 32'd1;
main_memory[4] = 32'd2;
main_memory[5] = 32'd3;
main_memory[6] = 32'd1;
main_memory[7] = 32'd2;
main_memory[8] = 32'd3;

//matrix B
main_memory[9] = 32'd1;
main_memory[10] = 32'd2;
main_memory[11] = 32'd3;
main_memory[12] = 32'd1;
main_memory[13] = 32'd2;
main_memory[14] = 32'd3;
main_memory[15] = 32'd1;
main_memory[16] = 32'd2;
main_memory[17] = 32'd3;


main_memory[18] = 32'd1;
main_memory[19] = 32'd2;
main_memory[20] = 32'd3;
main_memory[21] = 32'd1;
main_memory[22] = 32'd2;
main_memory[23] = 32'd3;
main_memory[24] = 32'd1;
main_memory[25] = 32'd2;
main_memory[26] = 32'd3;

end  

//matrix A
// main_memory[0] = 32'd1;
// main_memory[1] = 32'd2;
// main_memory[2] = 32'd3;
// main_memory[3] = 32'd1;
// main_memory[4] = 32'd2;
// main_memory[5] = 32'd3;
// main_memory[6] = 32'd1;
// main_memory[7] = 32'd2;
// main_memory[8] = 32'd3;

// //matrix B
// main_memory[9] = 32'd1;
// main_memory[10] = 32'd2;
// main_memory[11] = 32'd3;
// main_memory[12] = 32'd1;
// main_memory[13] = 32'd2;
// main_memory[14] = 32'd3;
// main_memory[15] = 32'd1;
// main_memory[16] = 32'd2;
// main_memory[17] = 32'd3;


always @(posedge clk) 
begin  
  if(write_enable)
  begin  
    main_memory[main_address] = write_data;
  end  
end  

assign read_data = (read_enable == 1'b1) ? main_memory[main_address]:32'd0;

endmodule

alu.v
module alu(clk,data_1,data_2,alu_cntrl,alu_out,zero);
    input[3:0]alu_cntrl;
    input clk;
    input[31:0]data_1, data_2;
    output reg[31:0] alu_out;
    output reg zero;

    always@(posedge clk)
    begin
        zero = 0;
        case(alu_cntrl)
            4'b0000: alu_out <= data_1 & data_2;
            4'b0001: alu_out <= data_1 | data_2;
            4'b0010: alu_out <= data_1 + data_2;
            4'b0011: alu_out <= data_1 - data_2;
            4'b0100: alu_out <= data_1 * data_2;
        endcase
        if(alu_out == 0)
            zero = 1;
    end
endmodule

alu_control_unit.v
module alu_control_unit(clk,func,alu_op,alu_control);

input clk;
input[5:0] func;
input[1:0] alu_op;
output[3:0] alu_control;

// wire[3:0] alu_control;
reg[3:0] alu_control;

always @(posedge clk)
begin
  case(alu_op)
    2'b00 : 
        alu_control = 4'b0010; // lw and sw
    2'b01 : 
        alu_control = 4'b0011; // beq
    2'b10 : // r type
        begin
        if(func == 6'b100000) //add
        begin
            alu_control = 4'b0010;
        end
        else if(func == 6'b100001) // mult
        begin
            alu_control = 4'b0100;
        end
        end
  endcase
end

endmodule

register_file.v
module register_file(clk,read_reg1,read_reg2,write_reg,write_data,reg_write,read_data1,read_data2);

input clk;
input[4:0] read_reg1;
input[4:0] read_reg2;
input[4:0] write_reg;
input[31:0] write_data;
input reg_write;
output[31:0] read_data1;
output[31:0] read_data2;

reg[31:0] read_data1;
reg[31:0] read_data2;

wire[4:0] read_reg1;
wire[4:0] read_reg2;
wire[4:0] write_reg;
// reg[15:0] write_data;
// reg[15:0] read_data1;
// reg[15:0] read_data2;

// reg[31:0] s0;
// reg[31:0] s1;
// reg[31:0] s2;
// reg[31:0] s3;
// reg[31:0] s4;
// reg[31:0] s5;
// reg[31:0] s6;
// reg[31:0] s7;

// reg[31:0] t0;
// reg[31:0] t1;
// reg[31:0] t2;
// reg[31:0] t3;
// reg[31:0] t4;
// reg[31:0] t5;
// reg[31:0] t6;
// reg[31:0] t7;

// reg[31:0] z0;
// reg[31:0] z1;
// reg[31:0] z2;
// reg[31:0] z3;
// reg[31:0] z4;
// reg[31:0] z5;
// reg[31:0] z6;
// reg[31:0] z7;

reg[31:0] all_registers[0:31]; //32 registers each of 32 bit(i.e 32 32bit regs)

//loop for initialising the all the registers
integer i;
initial 
begin  
  for(i = 0 ;i < 32 ;i = i + 1) 
        all_registers[i] <= 32'd0;  
end 

always @(posedge clk)
begin
  if (reg_write == 1) 
  begin
  all_registers[write_reg] <= write_data;
  end
  else
  begin
  read_data1 <= all_registers[read_reg1];
  read_data2 <= all_registers[read_reg2];
  end
end

//$display("%d %d",all_registers[0],all_registers[1]);

endmodule




// module register_decoder(clk,register, out);
//     input[4:0] register;
//     input clk;
//     output reg[31:0] out;
//     always@(posedge clk)
//     begin
//         case(register[2:0])
//             3'b000: out = 11;
//             3'b001: out = 23;
//             3'b010: out = 35;
//             3'b011: out = 9;
//             3'b100: out = 43;
//             3'b101: out = 2;
//             3'b110: out = 50;
//         endcase
//     end
// endmodule

control_unit.v
module control_unit(clk,opcode,reg_dst,memto_reg,alu_op,jump,branch,mem_read,mem_write,alu_src,reg_write);  
 
input clk;
input [5:0] opcode;

output reg[1:0] alu_op;
output reg memto_reg,reg_dst,jump, branch, mem_read, mem_write, alu_src, reg_write;

always @(*)  
begin 

//Default control signals
reg_dst = 1'b0;  
memto_reg = 1'b0;  
alu_op = 2'b00;  
jump = 1'b0;  
branch = 1'b0;  
mem_read = 1'b0;  
mem_write = 1'b0;  
alu_src = 1'b0;  
reg_write = 1'b0;    

    case(opcode)   
    6'b000000:  begin  //control lines for add/mult instruction  
                reg_dst = 1'b1;  
                memto_reg = 1'b0;  
                alu_op = 2'b10;  
                jump = 1'b0;  
                branch = 1'b0;  
                mem_read = 1'b0;  
                mem_write = 1'b0;  
                alu_src = 1'b0;  
                reg_write = 1'b1;  
                end  
        
    6'b000010:  begin //control lines for j instruction  
                reg_dst = 1'b0;  
                memto_reg = 1'b0;  
                alu_op = 2'b00;  
                jump = 1'b1;  
                branch = 1'b0;  
                mem_read = 1'b0;  
                mem_write = 1'b0;  
                alu_src = 1'b0;  
                reg_write = 1'b0;   
                end
    6'b100011:  begin //control lines for lw instruction 
                reg_dst = 1'b0;  
                memto_reg = 1'b1;  
                alu_op = 2'b00;  
                jump = 1'b0;  
                branch = 1'b0;  
                mem_read = 1'b1;  
                mem_write = 1'b0;  
                alu_src = 1'b1;  
                reg_write = 1'b1;  
                end  
    6'b101011:  begin //control lines for sw instruction 
                reg_dst = 1'b0;  
                memto_reg = 1'b0;  
                alu_op = 2'b00;  
                jump = 1'b0;  
                branch = 1'b0;  
                mem_read = 1'b0;  
                mem_write = 1'b1;  
                alu_src = 1'b1;  
                reg_write = 1'b0;
                end  
    6'b000100:  begin //control lines for beq instruction  
                reg_dst = 1'b0;  
                memto_reg = 1'b0;  
                alu_op = 2'b01;  
                jump = 1'b0;  
                branch = 1'b1;  
                mem_read = 1'b0;  
                mem_write = 1'b0;  
                alu_src = 1'b0;  
                reg_write = 1'b0;   
                end
    endcase  
end    


endmodule

instruction_memory.v
module instruction_memory(clk,pc, instruction);

input clk;
input[31:0] pc;

output[31:0] instruction;
reg[31:0] instruction;

//256 registers of 32-bits each
reg[31:0] instr_memory[255:0]; 


//MIPS assembly program in binary format
initial 
begin
    instr_memory[0] <= 32'b10001100000000010000000000100000;
    instr_memory[1] <= 32'b10001100000000100000000000100000;
    instr_memory[2] <= 32'b10001100000000110000000000100000;
    //instr_memory[2] <= 
    // instr_memory[3] <= 
    // instr_memory[4] <= 
    // instr_memory[5] <= 
    // instr_memory[6] <= 
    // instr_memory[7] <= 
    // instr_memory[8] <= 
    // instr_memory[9] <= 
    // instr_memory[10] <= 
    // instr_memory[11] <= 
    // instr_memory[12] <= 
    // instr_memory[13] <= 
    // instr_memory[14] <= 
    // instr_memory[15] <= 
    // instr_memory[16] <= 
    // instr_memory[17] <= 
    // instr_memory[18] <= 
    // instr_memory[19] <= 
    // instr_memory[20] <= 
    // instr_memory[21] <= 
    // instr_memory[22] <= 
    // instr_memory[23] <= 
    // instr_memory[24] <= 
    // instr_memory[25] <= 
    // instr_memory[26] <= 
    // instr_memory[27] <= 
    // instr_memory[28] <= 
    // instr_memory[29] <= 
    // instr_memory[30] <= 
    // instr_memory[31] <= 
    // instr_memory[32] <= 
    // instr_memory[33] <= 
    // instr_memory[34] <= 
    // instr_memory[35] <= 
    // instr_memory[36] <= 
    // instr_memory[37] <= 
    // instr_memory[38] <= 
    // instr_memory[39] <= 
    // instr_memory[40] <= 
end

always @(posedge clk)
begin
    instruction = instr_memory[pc];
end

endmodule

MIPS.v
/*MAIN MODULE*/
module mips(clk,reset,pc_nxt,result);

input clk;
input reset;

output[31:0] result;
output[31:0] pc_nxt;

reg[31:0] result;
/*PROGRAM COUNTER*/
// wire[31:0] pc_nxt;
reg[31:0] pc;
reg[31:0] extended;
// pc p_c(clk,reset,extended,branch,zero,pc,pc_nxt);
// assign pc = pc_nxt;
reg[31:0] adder1;
reg[31:0] adder2;
reg sel;
reg[31:0] pc_nxt;

always @(posedge clk)
begin
    if(reset)
    begin
        pc_nxt <= 31'd0;
    end
    else
    begin
        adder1 = pc+1;
        extended = extended << 2;
        adder2 = adder1+extended;
        sel = branch & zero;
        pc = sel ? adder2 : adder1;
        pc_nxt <= pc;
    end
    pc = pc_nxt;
    // $display("this is pc:");
    // $display("%d",pc);
end




/*INSTRUCTION MEMORY*/
wire[31:0] instruction;
instruction_memory IM(clk,pc,instruction);
// always @(posedge clk)
// begin
// $display("iam the instruction:");
// $display("%d",instruction);
// end


/*CONTROL UNIT*/
//Wires required
wire reg_dst, memto_reg, jump, branch, mem_read, mem_write, alu_src, reg_write;
wire[1:0] alu_op;
//Module
control_unit Control(clk,instruction[31:26],reg_dst,memto_reg,alu_op,jump,branch,mem_read,mem_write,alu_src,reg_write);  


/*REGISTER FILE*/
//Wires required
wire[4:0] write_reg;
wire[31:0] write_data,read_data1,read_data2;
// wire reg_write;
//Mux for destination register
assign write_reg = (reg_dst == 1) ? instruction[15:11]:instruction[20:16];  
//Module 
register_file Registers(clk,instruction[25:21],instruction[20:16],write_reg,write_data,reg_write,read_data1,read_data2);


/*ALU CONTROL*/
//Wires required
// wire[1:0] alu_op;
wire[3:0] alu_control;
//Module
alu_control_unit ALU_control(clk,instruction[5:0],alu_op,alu_control);


/*ALU*/
//Wires required
wire[31:0] data_2;
wire[31:0] alu_result;
wire zero;
initial begin
//Sign extender
assign extended[31:0] = {{8{instruction[15]}},instruction[15:0]};
end
//Mux for ALU input
assign data_2 = (alu_src == 1) ? extended:read_data2; 
//Module
alu ALU(clk,read_data1,data_2,alu_control,alu_result,zero);
// always @(posedge clk)
// begin
// $display("iam alu_result");
// $display("%d",alu_result);
// end


/*DATA MEMORY*/
//Wires required
wire[31:0] read_data;
//Module
data_memory_unit Data_memory(clk,alu_result,read_data2,mem_write,mem_read,read_data);

//Mux for writing back to the register file
assign write_data = (memto_reg == 1) ? read_data:alu_result;

initial begin
assign result = alu_result;
end
/*wire pc_nxt;
pc pc(clk,reset,extended,branch,zero,pc,pc_nxt);
pc = pc_nxt;*/

endmodule

main_tb.v
module main_tb;

reg clk;
reg reset;
wire[31:0] result;
wire[31:0] pc_nxt;

mips uut
(
    .clk(clk),
    .reset(reset),
    .result(result),
    .pc_nxt(pc_nxt)
);

initial
begin
  $dumpfile("out.vcd");
  $dumpvars(0,main_tb);

  clk = 1;
  reset = 1;

  #80
  reset = 0;

  #200
  $finish;
end

always
    #10 clk = ~clk;

endmodule

out.vcd
$date
	Tue Nov 27 00:02:17 2018
$end
$version
	Icarus Verilog
$end
$timescale
	1s
$end
$scope module main_tb $end
$var wire 32 ! result [31:0] $end
$var wire 32 " pc_nxt [31:0] $end
$var reg 1 # clk $end
$var reg 1 $ reset $end
$scope module uut $end
$var wire 1 # clk $end
$var wire 1 $ reset $end
$var wire 1 % zero $end
$var wire 5 & write_reg [4:0] $end
$var wire 32 ' write_data [31:0] $end
$var wire 1 ( reg_write $end
$var wire 1 ) reg_dst $end
$var wire 32 * read_data2 [31:0] $end
$var wire 32 + read_data1 [31:0] $end
$var wire 32 , read_data [31:0] $end
$var wire 1 - memto_reg $end
$var wire 1 . mem_write $end
$var wire 1 / mem_read $end
$var wire 1 0 jump $end
$var wire 32 1 instruction [31:0] $end
$var wire 32 2 data_2 [31:0] $end
$var wire 1 3 branch $end
$var wire 1 4 alu_src $end
$var wire 32 5 alu_result [31:0] $end
$var wire 2 6 alu_op [1:0] $end
$var wire 4 7 alu_control [3:0] $end
$var reg 32 8 adder1 [31:0] $end
$var reg 32 9 adder2 [31:0] $end
$var reg 32 : extended [31:0] $end
$var reg 32 ; pc [31:0] $end
$var reg 32 < pc_nxt [31:0] $end
$var reg 32 = result [31:0] $end
$var reg 1 > sel $end
$scope module ALU $end
$var wire 1 # clk $end
$var wire 32 ? data_2 [31:0] $end
$var wire 32 @ data_1 [31:0] $end
$var wire 4 A alu_cntrl [3:0] $end
$var reg 32 B alu_out [31:0] $end
$var reg 1 % zero $end
$upscope $end
$scope module ALU_control $end
$var wire 1 # clk $end
$var wire 6 C func [5:0] $end
$var wire 2 D alu_op [1:0] $end
$var reg 4 E alu_control [3:0] $end
$upscope $end
$scope module Control $end
$var wire 1 # clk $end
$var wire 6 F opcode [5:0] $end
$var reg 2 G alu_op [1:0] $end
$var reg 1 4 alu_src $end
$var reg 1 3 branch $end
$var reg 1 0 jump $end
$var reg 1 / mem_read $end
$var reg 1 . mem_write $end
$var reg 1 - memto_reg $end
$var reg 1 ) reg_dst $end
$var reg 1 ( reg_write $end
$upscope $end
$scope module Data_memory $end
$var wire 32 H address [31:0] $end
$var wire 1 # clk $end
$var wire 32 I main_address [31:0] $end
$var wire 1 / read_enable $end
$var wire 1 . write_enable $end
$var wire 32 J write_data [31:0] $end
$var wire 32 K read_data [31:0] $end
$upscope $end
$scope module IM $end
$var wire 1 # clk $end
$var wire 32 L pc [31:0] $end
$var reg 32 M instruction [31:0] $end
$upscope $end
$scope module Registers $end
$var wire 1 # clk $end
$var wire 5 N read_reg1 [4:0] $end
$var wire 5 O read_reg2 [4:0] $end
$var wire 1 ( reg_write $end
$var wire 32 P write_data [31:0] $end
$var wire 5 Q write_reg [4:0] $end
$var reg 32 R read_data1 [31:0] $end
$var reg 32 S read_data2 [31:0] $end
$var integer 32 T i [31:0] $end
$upscope $end
$upscope $end
$upscope $end
$enddefinitions $end
#0
$dumpvars
b100000 T
bx S
bx R
bx Q
bx P
bx O
bx N
bx M
b0 L
b0 K
bx J
bx I
bx H
b0 G
bx F
bx E
b0 D
bx C
bx B
bx A
bx @
bx ?
x>
bx =
b0 <
b0 ;
b0xxxxxxxxxxxxxxxxxxxxxxxx :
bx 9
bx 8
bx 7
b0 6
bx 5
04
03
bx 2
bx 1
00
0/
0.
0-
b0 ,
bx +
bx *
0)
0(
bx '
bx &
0%
1$
1#
b0 "
bx !
$end
#10
0#
#20
b100000 :
b1 &
b1 Q
b100000 C
b1 O
b0 N
b100011 F
b10 7
b10 A
b10 E
b10001100000000010000000000100000 1
b10001100000000010000000000100000 M
1#
#30
0#
#40
bx ,
bx K
bx '
bx P
b100000 2
b100000 ?
1(
14
1/
1-
b0 *
b0 J
b0 S
b0 +
b0 @
b0 R
1#
#50
0#
#60
b1011 '
b1011 P
b1011 ,
b1011 K
b100000 I
b100000 !
b100000 =
b100000 5
b100000 B
b100000 H
1(
14
1/
1-
1#
#70
0#
#80
b1 "
b1 <
b100000 2
b100000 ?
1(
14
1/
1-
bx *
bx J
bx S
b0 ;
b0 L
0>
b10000001 9
b100000 :
b1 8
1#
0$
#90
0#
#100
b100000 2
b100000 ?
b1 ;
b1 L
b100000 :
b1011 *
b1011 J
b1011 S
1(
14
1/
1-
1#
#110
0#
#120
b10 "
b10 <
b10 &
b10 Q
b10 O
b100000 2
b100000 ?
b10001100000000100000000000100000 1
b10001100000000100000000000100000 M
1(
14
1/
1-
b1 ;
b1 L
b10000010 9
b100000 :
b10 8
1#
#130
0#
#140
b100000 2
b100000 ?
b10 ;
b10 L
b100000 :
b0 *
b0 J
b0 S
1(
14
1/
1-
1#
#150
0#
#160
b11 "
b11 <
b11 &
b11 Q
b11 O
b100000 2
b100000 ?
b10001100000000110000000000100000 1
b10001100000000110000000000100000 M
1(
14
1/
1-
b1011 *
b1011 J
b1011 S
b10 ;
b10 L
b10000011 9
b100000 :
b11 8
1#
#170
0#
#180
b100000 2
b100000 ?
b11 ;
b11 L
b100000 :
b0 *
b0 J
b0 S
1(
14
1/
1-
1#
#190
0#
#200
b100 "
b100 <
bx &
bx Q
bx C
bx O
bx N
bx F
b100000 2
b100000 ?
bx 1
bx M
1(
14
1/
1-
b1011 *
b1011 J
b1011 S
b11 ;
b11 L
b10000100 9
b100000 :
b100 8
1#
#210
0#
#220
bx I
bx !
bx =
bx 5
bx B
bx H
b0 ,
b0 K
bx 2
bx ?
bx '
bx P
b100 ;
b100 L
b0xxxxxxxxxxxxxxxxxxxxxxxx :
bx *
bx J
bx S
bx +
bx @
bx R
0(
04
0/
0-
1#
#230
0#
#240
b101 "
b101 <
b100 ;
b100 L
bx 9
b0xxxxxxxxxxxxxxxxxxxxxxxx :
b101 8
1#
#250
0#
#260
b101 ;
b101 L
b0xxxxxxxxxxxxxxxxxxxxxxxx :
1#
#270
0#
#280
b110 "
b110 <
b101 ;
b101 L
b0xxxxxxxxxxxxxxxxxxxxxxxx :
b110 8
1#
